higgs_kernels/__init__.py
higgs_kernels/grids.py
higgs_kernels/grids.safetensors
higgs_kernels/hadamard.py
higgs_kernels/kernels.py
higgs_kernels/linear.py
higgs_kernels/py.typed
higgs_kernels/references.py
higgs_kernels/csrc/portable/dequant.cpp
higgs_kernels/csrc/portable/dequant.cu
higgs_kernels/csrc/portable/quant.cpp
higgs_kernels/csrc/portable/quant_bf16.cu
higgs_kernels/csrc/portable/quant_f16.cu
higgs_kernels-0.4.0.dist-info/METADATA
higgs_kernels-0.4.0.dist-info/WHEEL
higgs_kernels-0.4.0.dist-info/licenses/LICENSE
higgs_kernels-0.4.0.dist-info/RECORD
